pypey/__init__.py
pypey/dyct.py
pypey/dycts.py
pypey/func.py
pypey/pype.py
pypey/pypes.py
pypey/__pycache__/__init__.cpython-38.pyc
pypey/__pycache__/pype.cpython-38.pyc
pypey-3.0.2.dist-info/LICENSE
pypey-3.0.2.dist-info/METADATA
pypey-3.0.2.dist-info/WHEEL
pypey-3.0.2.dist-info/top_level.txt
pypey-3.0.2.dist-info/RECORD
