Metadata-Version: 2.1
Name: pypey
Version: 3.0.2
Summary: A library for building data pipelines
Home-page: https://github.com/JoseLlarena/pypey
Author: Jose Llarena
Author-email: jose.llarena@gmail.com
License: MIT
Keywords: pipes,lazy collections,streaming,combinators
Platform: UNKNOWN
Classifier: Development Status :: 5 - Production/Stable
Classifier: Environment :: Other Environment
Classifier: Intended Audience :: Developers
Classifier: License :: OSI Approved :: MIT License
Classifier: Natural Language :: English
Classifier: Operating System :: OS Independent
Classifier: Programming Language :: Python :: 3
Classifier: Programming Language :: Python :: 3.7
Classifier: Programming Language :: Python :: 3.8
Classifier: Programming Language :: Python :: 3.9
Classifier: Programming Language :: Python :: 3 :: Only
Classifier: Programming Language :: Python :: Implementation :: CPython
Classifier: Topic :: Utilities
Classifier: Topic :: Software Development :: Libraries
Requires-Python: >=3.7
License-File: LICENSE
Requires-Dist: more-itertools
Requires-Dist: pathos
Provides-Extra: test
Requires-Dist: pytest ; extra == 'test'
